LICENSE
MANIFEST.in
README.rst
setup.py
crdist/__init__.py
crdist/admin.py
crdist/apps.py
crdist/models.py
crdist/tests.py
crdist/urls.py
crdist/utils.py
crdist/views.py
crdist/widgets.py
crdist.egg-info/PKG-INFO
crdist.egg-info/SOURCES.txt
crdist.egg-info/dependency_links.txt
crdist.egg-info/not-zip-safe
crdist.egg-info/requires.txt
crdist.egg-info/top_level.txt
crdist/fixtures/data.json
crdist/locale/es/LC_MESSAGES/django.po
crdist/migrations/0001_initial.py
crdist/migrations/0002_load_intial_data.py
crdist/migrations/__init__.py
crdist/static/crdist/form.js
crdist/templates/form_ejemplo.html
crdist/templates/widgets/crdist.html