Metadata-Version: 1.1
Name: crdist
Version: 0.1.7
Summary: Costa Rican Geografic distribution for model admin in Django.
Home-page: https://github.com/solvo/crdist
Author: Luis Zarate Montero
Author-email: luis.zarate@solvosoft.com
License: GNU General Public License
Platform: OS Independent
Classifier: Environment :: Web Environment
Classifier: Framework :: Django
Classifier: Intended Audience :: Developers
Classifier: License :: OSI Approved :: GNU General Public License v3 or later (GPLv3+)
Classifier: Operating System :: OS Independent
Classifier: Programming Language :: Python
Classifier: Programming Language :: Python :: 2.7
Classifier: Programming Language :: Python :: 3.4
Classifier: Topic :: Internet :: WWW/HTTP
Classifier: Topic :: Internet :: WWW/HTTP :: Dynamic Content
